openhands/README.md
openhands/__init__.py
openhands/agenthub/README.md
openhands/agenthub/__init__.py
openhands/agenthub/browsing_agent/README.md
openhands/agenthub/browsing_agent/__init__.py
openhands/agenthub/browsing_agent/browsing_agent.py
openhands/agenthub/browsing_agent/prompt.py
openhands/agenthub/browsing_agent/response_parser.py
openhands/agenthub/browsing_agent/utils.py
openhands/agenthub/codeact_agent/README.md
openhands/agenthub/codeact_agent/__init__.py
openhands/agenthub/codeact_agent/action_parser.py
openhands/agenthub/codeact_agent/codeact_agent.py
openhands/agenthub/codeact_agent/micro/github.md
openhands/agenthub/codeact_agent/system_prompt.j2
openhands/agenthub/codeact_agent/user_prompt.j2
openhands/agenthub/codeact_swe_agent/README.md
openhands/agenthub/codeact_swe_agent/__init__.py
openhands/agenthub/codeact_swe_agent/action_parser.py
openhands/agenthub/codeact_swe_agent/codeact_swe_agent.py
openhands/agenthub/codeact_swe_agent/prompt.py
openhands/agenthub/codeact_swe_agent/response_parser.py
openhands/agenthub/delegator_agent/__init__.py
openhands/agenthub/delegator_agent/agent.py
openhands/agenthub/dummy_agent/__init__.py
openhands/agenthub/dummy_agent/agent.py
openhands/agenthub/micro/README.md
openhands/agenthub/micro/_instructions/actions/browse.md
openhands/agenthub/micro/_instructions/actions/delegate.md
openhands/agenthub/micro/_instructions/actions/finish.md
openhands/agenthub/micro/_instructions/actions/kill.md
openhands/agenthub/micro/_instructions/actions/message.md
openhands/agenthub/micro/_instructions/actions/read.md
openhands/agenthub/micro/_instructions/actions/reject.md
openhands/agenthub/micro/_instructions/actions/run.md
openhands/agenthub/micro/_instructions/actions/write.md
openhands/agenthub/micro/_instructions/format/action.md
openhands/agenthub/micro/_instructions/history_truncated.md
openhands/agenthub/micro/agent.py
openhands/agenthub/micro/coder/agent.yaml
openhands/agenthub/micro/coder/prompt.md
openfeet-0.9.9.dist-info/LICENSE
openfeet-0.9.9.dist-info/METADATA
openfeet-0.9.9.dist-info/WHEEL
openfeet-0.9.9.dist-info/entry_points.txt
openfeet-0.9.9.dist-info/RECORD
