Metadata-Version: 2.1
Name: openfeet
Version: 0.9.9
Summary: OpenHands: Code Less, Make More
Home-page: https://github.com/li-boxuan/OpenDevin
License: MIT
Author: OpenHands
Requires-Python: >=3.12,<4.0
Classifier: License :: OSI Approved :: MIT License
Classifier: Programming Language :: Python :: 3
Classifier: Programming Language :: Python :: 3.12
Requires-Dist: PyPDF2
Requires-Dist: anthropic[vertex]
Requires-Dist: bashlex (>=0.18,<0.19)
Requires-Dist: boto3
Requires-Dist: browsergym (==0.8.0)
Requires-Dist: datasets
Requires-Dist: dirhash
Requires-Dist: docker
Requires-Dist: e2b (>=0.17.1,<0.18.0)
Requires-Dist: fastapi
Requires-Dist: gevent (>=24.2.1,<25.0.0)
Requires-Dist: google-cloud-aiplatform
Requires-Dist: google-generativeai
Requires-Dist: grep-ast (==0.3.3)
Requires-Dist: html2text
Requires-Dist: jinja2 (>=3.1.3,<4.0.0)
Requires-Dist: json-repair
Requires-Dist: litellm
Requires-Dist: minio (>=7.2.8,<8.0.0)
Requires-Dist: numpy
Requires-Dist: pandas
Requires-Dist: pathspec (>=0.12.1,<0.13.0)
Requires-Dist: pexpect
Requires-Dist: protobuf (>=4.21.6,<6.0.0)
Requires-Dist: pyarrow (==17.0.0)
Requires-Dist: pyjwt (>=2.9.0,<3.0.0)
Requires-Dist: pylatexenc
Requires-Dist: python-docx
Requires-Dist: python-dotenv
Requires-Dist: python-frontmatter (>=1.1.0,<2.0.0)
Requires-Dist: python-multipart
Requires-Dist: python-pptx
Requires-Dist: seaborn
Requires-Dist: tenacity (>=8.5.0,<9.0.0)
Requires-Dist: termcolor
Requires-Dist: toml
Requires-Dist: tornado
Requires-Dist: tree-sitter (==0.21.3)
Requires-Dist: types-toml
Requires-Dist: uvicorn
Requires-Dist: zope-interface (==7.0.3)
Project-URL: Repository, https://github.com/li-boxuan/OpenDevin
